[
  {
    "title": "欢迎您体验这个迷你steemit小游戏",
    "content": "希望通过这个迷你小游戏，能让您尽快了解steemit的基本功能，如何玩转CN区，以及如何赚到大把大把的steem币哟！^_^",
    "tags": [
      "mini-steemit"
    ]
  },
  {
    "title": "如何快速注册steemit账号",
    "content": "嗯，您可以尝试 https://cnsteem.io/ 花一点小钱，快速注册成功！",
    "tags": [
      "mini-steemit",
      "cnsteem.io"
    ]
  },
  {
    "title": "justyy 银行是什么",
    "content": "Yep！steemit CN区的首家银行就是 @justyy 开办的。代理Steem Power给他，不仅可以获得赞的回报，还能每天拿不少的利息哟！快去试试。",
    "tags": [
      "mini-steemit",
      "justyy"
    ]
  },
  {
    "title": "来参加一下月旦评吧！大伟哥 @rivalhw 在召唤你",
    "content": "话说月旦评是大家施展文采的好去处。内容不限，包括但不限于文学、短篇、小说、散文、诗歌等，须个人原创，杜绝盗版、抄袭。",
    "tags": [
      "mini-steemit",
      "cn-reader"
    ]
  },
  {
    "title": "三个一",
    "content": "一诗，一画，一心声。来来来，大家一起三个一；幸好不是三缺一，打麻将差一个...",
    "tags": [
      "mini-steemit",
      "cn-31"
    ]
  },
  {
    "title": "华语好声音，身为麦霸的你不要错过哟！",
    "content": "这声音美的让人起鸡皮疙瘩哒，简直陶醉本尊了，快扶我一下...",
    "tags": [
      "mini-steemit",
      "cn-voice"
    ]
  }
]